<?xml version="1.0" encoding="UTF-8" standalone="no"?>
<MeteoInfo File="milconfig.xml" Type="configurefile">
  <Path OpenPath="D:\Working\MIScript\Jython\mis\traj">
    <RecentFolder Folder="D:\Working\MIScript\Jython"/>
    <RecentFolder Folder="D:\Working\MIScript"/>
    <RecentFolder Folder="D:\Working\MIScript\mywork"/>
    <RecentFolder Folder="D:\Working\MIScript\Jython\mis\plot_types"/>
    <RecentFolder Folder="D:\Working\MIScript\Jython\mis\io"/>
    <RecentFolder Folder="D:\Working\MIScript\Jython\mis\micaps"/>
    <RecentFolder Folder="D:\Working\MIScript\Jython\mis\netcdf"/>
    <RecentFolder Folder="D:\Temp\test"/>
    <RecentFolder Folder="D:\Working\MIScript\mywork\verification"/>
    <RecentFolder Folder="D:\Working\MIScript\Jython\mis"/>
  </Path>
  <Font>
    <TextFont FontName="宋体" FontSize="15"/>
  </Font>
  <Startup MainFormLocation="148,84" MainFormSize="1152,850"/>
</MeteoInfo>
